[
    {
        "id": "1",
        "nombre": "Kola Hipinto 1.5L",
        "Precio": "$6.000",
        "imagen":"kola1.5.jpg"
    },
    {
        "id": "2",
        "nombre": "Kola Hipinto 400ml",
        "Precio": "$3.000",
        "imagen":"kola400ml.jpg"
    },
    {
        "id": "3",
        "nombre": "Manzana Postobon 1.5L",
        "Precio": "$6.000",
        "imagen":"manzana.webp"
    },
    {
        "id": "4",
        "nombre": "Manzana Postobon 400ml",
        "Precio": "$3.000",
        "imagen":"manzana400ml.jpg"
    },
    {
        "id": "5",
        "nombre": "Uva Postobon 1.5L",
        "Precio": "$6.000",
        "imagen":"uva1.5.png"
    },
    {
        "id": "6",
        "nombre": "Uva Postobon 400ml",
        "Precio": "$3.000",
        "imagen":"uva400ml.webp"
    },
    {
        "id": "7",
        "nombre": "Naranja Postobon 1.5L",
        "Precio": "$6.000",
        "imagen":"naranja1.5.jpg"
    },
    {
        "id": "8",
        "nombre": "Naranja Postobon 400ml",
        "Precio": "$3.000",
        "imagen":"naranja400ml.webp"
    },
    {
        "id": "9",
        "nombre": "Piña Hipinto 1.5L",
        "Precio": "$6.000",
        "imagen":"piña.webp"
    },
    {
        "id": "10",
        "nombre": "Piña Hipinto 400ml",
        "Precio": "$3.000",
        "imagen":"piña.webp"
    },
    {
        "id": "11",
        "nombre": "Colombiana la nuestra 400ml",
        "Precio": "$3.000",
        "imagen":"colombiana400ml.png"
    },
    {
        "id": "12",
        "nombre": "Coca Cola Sabor Original 1.5L",
        "Precio": "$6.000",
        "imagen":"cocacola1.5.webp"
    },
    {
        "id": "13",
        "nombre": "Coca Cola Sabor Original 400ml",
        "Precio": "$3.000",
        "imagen":"cocacola400ml.jpg"
    },
    {
        "id": "14",
        "nombre": "Agua 600ml",
        "Precio": "$3.000",
        "imagen":"agua600ml.webp"
    },
    {
        "id": "15",
        "nombre": "Jugo Hit Mango 1L",
        "Precio": "$6.000",
        "imagen":"jugomango.png"
    },{
        "id": "16",
        "nombre": "Jugo Hit Mora 1L",
        "Precio": "$6.000",
        "imagen":"jugomora.webp"
    },
    {
        "id": "17",
        "nombre": "Jugo Hit Tropical 1L",
        "Precio": "$6.000",
        "imagen":"jugotropical.png"
    },
    {
        "id": "18",
        "nombre": "Jugo Hit Naranja piña 1L",
        "Precio": "$6.000",
        "imagen":"jugonaranjapiña.webp"
    },
    {
        "id": "19",
        "nombre": "Jugo Natural Maracuya",
        "Precio": "$6.000",
        "imagen":"maracuya.jpg"
    },
    {
        "id": "20",
        "nombre": "Jugo Natural Naranja",
        "Precio": "$6.000",
        "imagen":"naranja.jpg"
    },
    {
        "id": "21",
        "nombre": "Jugo Natural Mandarina",
        "Precio": "$6.000",
        "imagen":"jugoMandarina.jpg"
    },
    {
        "id": "22",
        "nombre": "Jugo Natural Limón",
        "Precio": "$6.000",
        "imagen":"jugoLimon.jpg"
    },
    {
        "id": "23",
        "nombre": "Jugo Natural Fresa",
        "Precio": "$6.000",
        "imagen":"jugoFresa.jpg"
    }
] 